oceanscript.py
oceanscript-2.3.0.dist-info/LICENSE
oceanscript-2.3.0.dist-info/METADATA
oceanscript-2.3.0.dist-info/WHEEL
oceanscript-2.3.0.dist-info/top_level.txt
oceanscript-2.3.0.dist-info/RECORD
